pjdev_pydantic/__about__.py
pjdev_pydantic/__init__.py
pjdev_pydantic/models.py
pjdev_pydantic/onepassword_utils.py
pjdev_pydantic-4.6.3.dist-info/METADATA
pjdev_pydantic-4.6.3.dist-info/WHEEL
pjdev_pydantic-4.6.3.dist-info/licenses/LICENSE.txt
pjdev_pydantic-4.6.3.dist-info/RECORD
