Metadata-Version: 2.4
Name: pjdev-pydantic
Version: 4.6.3
Project-URL: Documentation, https://gitlab.purplejay.net/keystone/python/-/tree/main/pjdev-pydantic/README.md
Project-URL: Issues, https://gitlab.purplejay.net/keystone/python/-/issues
Project-URL: Source, https://gitlab.purplejay.net/keystone/python
Author-email: Purple Jay LLC <developers@purplejay.io>
License-Expression: MIT
License-File: LICENSE.txt
Classifier: Development Status :: 4 - Beta
Classifier: Programming Language :: Python
Classifier: Programming Language :: Python :: 3.12
Classifier: Programming Language :: Python :: Implementation :: CPython
Classifier: Programming Language :: Python :: Implementation :: PyPy
Requires-Python: >=3.12
Requires-Dist: loguru
Requires-Dist: nest-asyncio
Requires-Dist: onepassword-sdk
Requires-Dist: pydantic-settings>=2.4.0
Requires-Dist: pydantic>=2.8.2
